opengsl/__init__.py
opengsl/config/__init__.py
opengsl/config/util.py
opengsl/config/appnp/appnp_amazon-ratings.yaml
opengsl/config/appnp/appnp_blogcatalog.yaml
opengsl/config/appnp/appnp_citeseer.yaml
opengsl/config/appnp/appnp_cora.yaml
opengsl/config/appnp/appnp_flickr.yaml
opengsl/config/appnp/appnp_hetero.yaml
opengsl/config/appnp/appnp_minesweeper.yaml
opengsl/config/appnp/appnp_pubmed.yaml
opengsl/config/appnp/appnp_questions.yaml
opengsl/config/appnp/appnp_roman-empire.yaml
opengsl/config/appnp/appnp_wiki-cooc.yaml
opengsl/config/bmgcn/bmgcn_cora.yaml
opengsl/config/cogsl/cogsl_amazon-ratings.yaml
opengsl/config/cogsl/cogsl_blogcatalog.yaml
opengsl/config/cogsl/cogsl_citeseer.yaml
opengsl/config/cogsl/cogsl_cora.yaml
opengsl/config/cogsl/cogsl_flickr.yaml
opengsl/config/cogsl/cogsl_minesweeper.yaml
opengsl/config/cogsl/cogsl_pubmed.yaml
opengsl/config/cogsl/cogsl_roman-empire.yaml
opengsl/config/cogsl/cogsl_wikics.yaml
opengsl/config/gat/gat_amazon-ratings.yaml
opengsl/config/gat/gat_blogcatalog.yaml
opengsl/config/gat/gat_citeseer.yaml
opengsl/config/gat/gat_cora.yaml
opengsl/config/gat/gat_flickr.yaml
opengsl/config/gat/gat_minesweeper.yaml
opengsl/config/gat/gat_pubmed.yaml
opengsl/config/gat/gat_questions.yaml
opengsl/config/gat/gat_roman-empire.yaml
opengsl/config/gat/gat_wiki-cooc.yaml
opengsl/config/gaug/gaug_amazon-ratings.yaml
opengsl/config/gaug/gaug_blogcatalog.yaml
opengsl/config/gaug/gaug_blogcatalog_appnp.yaml
opengsl/config/gaug/gaug_blogcatalog_gin.yaml
opengsl/config/gaug/gaug_citeseer.yaml
opengsl/config/gaug/gaug_cora.yaml
opengsl/config/gaug/gaug_cora_gin.yaml
opengsl/config/gaug/gaug_csbm20.yaml
opengsl/config/gaug/gaug_csbm40.yaml
opengsl/config/gaug/gaug_csbm60.yaml
opengsl/config/gaug/gaug_csbm80.yaml
opengsl/config/gaug/gaug_flickr.yaml
opengsl/config/gaug/gaug_minesweeper.yaml
opengsl/config/gaug/gaug_pubmed.yaml
opengsl/config/gaug/gaug_roman-empire.yaml
opengsl/config/gaug/gaug_roman-empire_appnp.yaml
opengsl-0.0.55.dist-info/LICENSE
opengsl-0.0.55.dist-info/METADATA
opengsl-0.0.55.dist-info/WHEEL
opengsl-0.0.55.dist-info/top_level.txt
opengsl-0.0.55.dist-info/RECORD
