Metadata-Version: 2.1
Name: opengsl
Version: 0.0.55
Summary: A comprehensive benchmark for Graph Structure Learning.
Home-page: https://github.com/OpenGSL/OpenGSL
Author: Zhiyao Zhou, Sheng Zhou, Bochao Mao, Xuanyi Zhou
Keywords: AI,GNN,graph structure learning
Classifier: Programming Language :: Python :: 3.7
Classifier: Programming Language :: Python :: 3.8
Classifier: Programming Language :: Python :: 3.9
Classifier: Programming Language :: Python :: 3.10
Classifier: Intended Audience :: Developers
Classifier: Intended Audience :: Science/Research
Requires-Python: >=3.7.0
License-File: LICENSE
Requires-Dist: ruamel.yaml
Requires-Dist: pandas
Requires-Dist: scipy
Requires-Dist: scikit-learn
Requires-Dist: pyro-api ==0.1.2
Requires-Dist: pyro-ppl ==1.8.0
Requires-Dist: numba
